pytorch_eo/__init__.py
pytorch_eo/config/__init__.py
pytorch_eo/config/config.py
pytorch_eo/config/credentials.py
pytorch_eo/datasets/CategoricalImageDataset.py
pytorch_eo/datasets/ConcatDataset.py
pytorch_eo/datasets/RGBImageDataset.py
pytorch_eo/datasets/RasterioImageDataset.py
pytorch_eo/datasets/SensorImageDataset.py
pytorch_eo/datasets/SingleBandImageDataset.py
pytorch_eo/datasets/__init__.py
pytorch_eo/datasets/big_earth_net/BigEarthNet.py
pytorch_eo/datasets/big_earth_net/__init__.py
pytorch_eo/datasets/big_earth_net/utils.py
pytorch_eo/datasets/deep_globe_road_extraction/DeepGlobeRoadExtraction.py
pytorch_eo/datasets/deep_globe_road_extraction/__init__.py
pytorch_eo/datasets/eotdl_dataset/EOTDLDataset.py
pytorch_eo/datasets/eotdl_dataset/__init__.py
pytorch_eo/datasets/eurosat/EuroSAT.py
pytorch_eo/datasets/eurosat/EuroSATBase.py
pytorch_eo/datasets/eurosat/EuroSATRGB.py
pytorch_eo/datasets/eurosat/__init__.py
pytorch_eo/datasets/eurosat/utils.py
pytorch_eo/datasets/land_cover_net/LandCoverNet.py
pytorch_eo/datasets/land_cover_net/__init__.py
pytorch_eo/datasets/sen12floods/__init__.py
pytorch_eo/datasets/sen12floods/sen12floods.py
pytorch_eo/datasets/sen12floods/utils.py
pytorch_eo/datasets/sen12ms/Sen12MS.py
pytorch_eo/datasets/sen12ms/__init__.py
pytorch_eo/datasets/sensors/__init__.py
pytorch_eo/datasets/sensors/sensors.py
pytorch_eo/datasets/sensors/utils.py
pytorch_eo/datasets/ucmerced/UCMercedLandUse.py
pytorch_eo/datasets/ucmerced/__init__.py
pytorch_eo/datasets/ucmerced/utils.py
pytorch_eo/metrics/__init__.py
pytorch_eo/metrics/classification.py
pytorch_eo/metrics/segmentation.py
pytorch_eo/tasks/BaseTask.py
pytorch_eo/tasks/__init__.py
pytorch_eo/tasks/classification/ImageClassification.py
pytorch_eo/tasks/classification/ImageMultilabelClassification.py
pytorch_eo/tasks/classification/__init__.py
pytorch_eo/tasks/segmentation/ImageSegmentation.py
pytorch_eo/tasks/segmentation/__init__.py
pytorch_eo/utils/__init__.py
pytorch_eo-2025.4.3.dist-info/METADATA
pytorch_eo-2025.4.3.dist-info/WHEEL
pytorch_eo-2025.4.3.dist-info/licenses/LICENSE
pytorch_eo-2025.4.3.dist-info/RECORD
