Metadata-Version: 2.4
Name: pytorch-eo
Version: 2025.4.3
Summary: Deep Learning for Earth Observation
Author-email: earthpulse <it@earthpulse.es>
License-Expression: MIT
License-File: LICENSE
Requires-Python: >=3.12
Requires-Dist: albumentations>=2.0.5
Requires-Dist: einops>=0.8.1
Requires-Dist: lightning>=2.5.1
Requires-Dist: rasterio>=1.4.3
Requires-Dist: scikit-image>=0.25.2
Requires-Dist: scikit-learn>=1.6.1
Requires-Dist: torch>=2.6.0
Requires-Dist: torchmetrics>=1.7.0
Requires-Dist: torchvision>=0.21.0
